odoo/addons/website_img_dimension/README.rst
odoo/addons/website_img_dimension/__init__.py
odoo/addons/website_img_dimension/__manifest__.py
odoo/addons/website_img_dimension/i18n/ca.po
odoo/addons/website_img_dimension/i18n/es.po
odoo/addons/website_img_dimension/i18n/fr.po
odoo/addons/website_img_dimension/i18n/it.po
odoo/addons/website_img_dimension/i18n/pt_BR.po
odoo/addons/website_img_dimension/i18n/website_img_dimension.pot
odoo/addons/website_img_dimension/readme/CONTRIBUTORS.rst
odoo/addons/website_img_dimension/readme/DESCRIPTION.rst
odoo/addons/website_img_dimension/readme/USAGE.rst
odoo/addons/website_img_dimension/static/description/icon.png
odoo/addons/website_img_dimension/static/description/index.html
odoo/addons/website_img_dimension/static/description/screenshot.png
odoo/addons/website_img_dimension/static/src/js/website_img_dimension.tooltip.js
odoo/addons/website_img_dimension/templates/assets.xml
odoo12_addon_website_img_dimension-12.0.1.0.0.99.dev13.dist-info/METADATA
odoo12_addon_website_img_dimension-12.0.1.0.0.99.dev13.dist-info/WHEEL
odoo12_addon_website_img_dimension-12.0.1.0.0.99.dev13.dist-info/top_level.txt
odoo12_addon_website_img_dimension-12.0.1.0.0.99.dev13.dist-info/RECORD
